learnpy/__init__.py
learnpy/version.py
learnpy-0.1.0.dist-info/METADATA
learnpy-0.1.0.dist-info/WHEEL
learnpy-0.1.0.dist-info/top_level.txt
learnpy-0.1.0.dist-info/RECORD
