Metadata-Version: 2.1
Name: learnpy
Version: 0.1.0
Summary: learnpy
Home-page: http://github.com/zhiqingxiao/learnpy/
Author: Zhiqing Xiao
Author-email: xzq.xiaozhiqing@gmail.com
Classifier: Programming Language :: Python
Classifier: Intended Audience :: Science/Research
